gm_canada_ai-0.1.data/scripts/gm-canada-ai
package/__init__.py
package/my_classes.py
package/utilities.py
package/nlp/__init__.py
package/nlp/embedding.py
package/nlp/preprocessing.py
package/nlp/summarization.py
package/symspellpy/__init__.py
package/symspellpy/editdistance.py
package/symspellpy/helpers.py
package/symspellpy/symspellpy.py
gm_canada_ai-0.1.dist-info/METADATA
gm_canada_ai-0.1.dist-info/WHEEL
gm_canada_ai-0.1.dist-info/top_level.txt
gm_canada_ai-0.1.dist-info/RECORD
