Metadata-Version: 2.1
Name: gm-canada-ai
Version: 0.1
Summary: arief's package
Home-page: https://bitbucket.gm.com/scm/atwc171657/gmpackages
Author: arief koesdwiady
Author-email: ariefbarkah@gmail.com
License: UNKNOWN
Platform: UNKNOWN
Classifier: Programming Language :: Python :: 3
Classifier: License :: OSI Approved :: MIT License
Classifier: Operating System :: OS Independent
